{
  "packet_id": "PKT-Y02",
  "applicant_id": "Y002",
  "decision_packet": {
    "final_recommendation": "accept",
    "reason_codes": ["keyword_match"],
    "explanation_present": true,
    "documentation_present": true
  },
  "applicant_data": {
    "resume_parse_confidence": 0.85,
    "missing_fields": [],
    "data_completeness_score": 0.90
  },
  "keyword_assessment": {
    "keyword_score": 0.65,
    "overreliance_risk": true,
    "semantic_match_available": false,
    "keyword_rules_transparent": true,
    "possible_proxy_terms_detected": false
  },
  "oversight_features": {
    "decision_observability_score": 0.80,
    "contradiction_flag": false,
    "insufficient_explanation_flag": false,
    "vendor_transparency_limited": false
  }
}
